easyPyMySQL/Table.py
easyPyMySQL/TableField.py
easyPyMySQL/TableLine.py
easyPyMySQL/__init__.py
easyPyMySQL/easyPyMySQL.py
easyPyMySQL-1.5.dist-info/METADATA
easyPyMySQL-1.5.dist-info/WHEEL
easyPyMySQL-1.5.dist-info/top_level.txt
easyPyMySQL-1.5.dist-info/RECORD
