Metadata-Version: 2.1
Name: easyPyMySQL
Version: 1.5
Summary: 简单易用的数据库ORM模块
Home-page: https://github.com/AkiYama-Ryou/easyPyMySQL
Author: ChenRuohan
Author-email: crh51306@gmail.com
License: UNKNOWN
Platform: UNKNOWN
